{"urls":[
{"name":"🆙圥忈1","url":"https://gitlab.com/dokiss1/tvbox/-/raw/master/doki-18+.json"},
{"name":"🆙圥忈2","url":"https://gitlab.com/dokiss1/tvbox/-/raw/master/doki-19+.json"},
{"name":"🆙南宫","url":"https://raw.kkgithub.com/bizhangjie/CatVodSpider/main/json/index18.json"},
{"name":"🆙苦瓜","url":"https://raw.kkgithub.com/bizhangjie/CatVodSpider/main/json/18sex.json"},
{"name":"🆙九零","url":"https://raw.kkgithub.com/bizhangjie/CatVodSpider/main/json/18sexN.json"},
{"name":"🆙动态","url":"https://raw.kkgithub.com/supermeguo/BoxRes/main/Myuse/catcr.json"},
{"name":"🆙认同","url":"https://raw.kkgithub.com/supermeguo/BoxRes/main/Myuse/18sex.txt"},
{"name":"🆙雨虹","url":"https://raw.kkgithub.com/supermeguo/BoxRes/main/Myuse/oldcatcr.json"},
{"name":"🆙得分","url":"https://raw.kkgithub.com/SSM0415/apptest/main/avnetwork18x.txt"},
{"name":"🆙公会","url":"https://raw.kkgithub.com/SSM0415/apptest/main/18cn.json"},
{"name":"🆙变化","url":"https://raw.kkgithub.com/liuwei0704/66/master/jkjynb.json"},
{"name":"🆙环游","url":"https://raw.kkgithub.com/liuwei0704/66/master/csdy.json"},
{"name":"🆙狐狸","url":"https://raw.kkgithub.com/liuwei0704/66/master/147852.json"},
{"name":"🆙表格","url":"https://raw.kkgithub.com/liuwei0704/66/master/zydy.json"},
{"name":"🆙体内","url":"https://raw.kkgithub.com/liuwei0704/66/master/pro.json"},
{"name":"🆙精品","url":"https://raw.kkgithub.com/wwb521/live/main/video.json"},
{"name":"🆙钢铁","url":"https://raw.kkgithub.com/qist/tvbox/master/9918.json"},
{"name":"🆙还原","url":"https://raw.kkgithub.com/shichuanenhui/TvBox/main/jav.json"},
{"name":"🆙册亨","url":"https://raw.kkgithub.com/guot55/yg/main/pro.json"},
{"name":"🆙广泛","url":"https://raw.kkgithub.com/jessic01/box1/main/18.json"},
{"name":"🆙分别","url":"https://raw.kkgithub.com/c120487/00/main/05155.txt"},
{"name":"🆙很久","url":"https://raw.kkgithub.com/qaz1371041/tvbox/main/18.json"},
{"name":"🆙最新","url":"https://raw.kkgithub.com/fish2018/tvbox/master/%E6%9C%80%E6%96%B0.txt"},
{"name":"🆙螺丝","url":"https://raw.kkgithub.com/xiaolinshao/linshao/main/18.json"},
{"name":"🆙佰欣园","url":"https://raw.kkgithub.com/chengxueli818913/TV/main/api.json"},
{"name":"🆙新视觉1","url":"https://raw.kkgithub.com/sqspot/tac/main/18.js"},
{"name":"🆙新视觉2","url":"https://raw.kkgithub.com/sqspot/tac/main/18.json"},
{"name":"🆙新视觉3","url":"https://raw.kkgithub.com/sqspot/tac/main/18(1).js"},
{"name":"🆙猫影视","url":"https://raw.kkgithub.com/Dong-learn9/TVBox-zyjk/main/18.json"},
{"name":"🆙挺好专享","url":"https://raw.kkgithub.com/ZTHA000/tvbox/main/thzx1.json"},
{"name":"二分","url":"https://raw.kkgithub.com/c120487/00/main/1028c.txt"},
{"name":"福田","url":"https://raw.kkgithub.com/c120487/00/main/00tvx1.txt"},
{"name":"古井","url":"https://raw.kkgithub.com/c120487/00/main/00tvx0.txt"},
{"name":"德浩","url":"https://raw.kkgithub.com/2hacc/TVBox/main/h/h.json"},
{"name":"月光","url":"https://raw.kkgithub.com/guot55/YGBH/main/prox3.json"},
{"name":"果然","url":"https://raw.kkgithub.com/jigedos/tvbox2/main/thzx1.json"},
{"name":"彩色","url":"https://raw.kkgithub.com/shiran588/TVBox/main/cr.json"},
{"name":"风度","url":"https://raw.kkgithub.com/yschaizhen/xian/main/hh"},
{"name":"司机","url":"https://raw.kkgithub.com/tv189ymail/ku2023/main/SMTT/司机.json"},
{"name":"蜘蛛","url":"https://raw.kkgithub.com/xfcjp/xfcjp.github.io/master/adult.json"},
{"name":"电单","url":"https://raw.kkgithub.com/zhanghong1983/tvboxzy/main/SEX.json"},
{"name":"唐僧魔盒","url":"https://raw.kkgithub.com/guot55/YGBH/main/tsys.json"}]}
